toppath/__init__.py
toppath/path.py
toppath-2025.6.4.dist-info/licenses/LICENSE.txt
toppath-2025.6.4.dist-info/METADATA
toppath-2025.6.4.dist-info/WHEEL
toppath-2025.6.4.dist-info/top_level.txt
toppath-2025.6.4.dist-info/RECORD
